{
  "summary": {
    "symbols": 60,
    "withTrades": 54,
    "improved": 16,
    "regressed": 19,
    "neutral": 19,
    "v11AvgPF": 1.0879704869494617,
    "v11TotalTrades": 195,
    "v11AvgWR": 50.76923076923077,
    "v11AvgNet": -0.023903180833333617
  },
  "results": [
    {
      "symbol": "SSE:603203",
      "totalTrades": 1,
      "wins": 0,
      "losses": 1,
      "winRate": 0,
      "netProfitPct": -0.2741135099999999,
      "profitFactor": 0,
      "maxDrawdownPct": 0.3734472099999984,
      "v10Trades": 3,
      "v10WinRate": 66.66666666666666,
      "v10PF": 0.8635886606741211,
      "v6PF": 1.615,
      "pfDelta10": -0.8635886606741211,
      "pfDelta6": -1.615
    },
    {
      "symbol": "SSE:603040",
      "totalTrades": 2,
      "wins": 1,
      "losses": 1,
      "winRate": 50,
      "netProfitPct": -0.08112187600000006,
      "profitFactor": 0.36228600088202423,
      "maxDrawdownPct": 0.3199943292565983,
      "v10Trades": 3,
      "v10WinRate": 33.33333333333333,
      "v10PF": 0.05647569965340193,
      "v6PF": 0.2,
      "pfDelta10": 0.3058103012286223,
      "pfDelta6": 0.16228600088202422
    },
    {
      "symbol": "SSE:603638",
      "totalTrades": 0,
      "wins": 0,
      "losses": 0,
      "winRate": 0,
      "netProfitPct": 0,
      "profitFactor": 0,
      "maxDrawdownPct": 0,
      "v10Trades": 2,
      "v10WinRate": 100,
      "v10PF": 0,
      "v6PF": 0,
      "pfDelta10": 0,
      "pfDelta6": 0
    },
    {
      "symbol": "SZSE:002983",
      "totalTrades": 3,
      "wins": 2,
      "losses": 1,
      "winRate": 66.66666666666666,
      "netProfitPct": 0.2631551299999998,
      "profitFactor": 1.4418069567382126,
      "maxDrawdownPct": 0.7175595399999875,
      "v10Trades": 3,
      "v10WinRate": 66.66666666666666,
      "v10PF": 1.1940780084083213,
      "v6PF": 1.724,
      "pfDelta10": 0.24772894832989123,
      "pfDelta6": -0.2821930432617874
    },
    {
      "symbol": "SZSE:000988",
      "totalTrades": 5,
      "wins": 2,
      "losses": 3,
      "winRate": 40,
      "netProfitPct": -1.7707750710000025,
      "profitFactor": 0.2122294696500111,
      "maxDrawdownPct": 2.5258296044484982,
      "v10Trades": 7,
      "v10WinRate": 28.57142857142857,
      "v10PF": 0.23559580410058523,
      "v6PF": 0,
      "pfDelta10": -0.023366334450574122,
      "pfDelta6": 0.2122294696500111
    },
    {
      "symbol": "SZSE:000951",
      "totalTrades": 1,
      "wins": 0,
      "losses": 1,
      "winRate": 0,
      "netProfitPct": -0.20507619600000182,
      "profitFactor": 0,
      "maxDrawdownPct": 0.3795878519999969,
      "v10Trades": 4,
      "v10WinRate": 50,
      "v10PF": 1.1304092383967108,
      "v6PF": 1.591,
      "pfDelta10": -1.1304092383967108,
      "pfDelta6": -1.591
    },
    {
      "symbol": "SSE:603300",
      "totalTrades": 1,
      "wins": 0,
      "losses": 1,
      "winRate": 0,
      "netProfitPct": -0.45725215200000036,
      "profitFactor": 0,
      "maxDrawdownPct": 0.45725215200000097,
      "v10Trades": 3,
      "v10WinRate": 0,
      "v10PF": 0,
      "v6PF": 0,
      "pfDelta10": 0,
      "pfDelta6": 0
    },
    {
      "symbol": "SSE:600547",
      "totalTrades": 3,
      "wins": 2,
      "losses": 1,
      "winRate": 66.66666666666666,
      "netProfitPct": 1.1782494550000011,
      "profitFactor": 3.764660827756615,
      "maxDrawdownPct": 0.47714914000000863,
      "v10Trades": 7,
      "v10WinRate": 28.57142857142857,
      "v10PF": 0.7010578768297601,
      "v6PF": 0.773,
      "pfDelta10": 3.063602950926855,
      "pfDelta6": 2.991660827756615
    },
    {
      "symbol": "SSE:603766",
      "totalTrades": 10,
      "wins": 7,
      "losses": 3,
      "winRate": 70,
      "netProfitPct": 2.0764151980000034,
      "profitFactor": 2.4303950573227313,
      "maxDrawdownPct": 0.9692470659999962,
      "v10Trades": 13,
      "v10WinRate": 53.84615384615385,
      "v10PF": 1.7930677169011378,
      "v6PF": 2.263,
      "pfDelta10": 0.6373273404215936,
      "pfDelta6": 0.1673950573227314
    },
    {
      "symbol": "SSE:603529",
      "totalTrades": 0,
      "wins": 0,
      "losses": 0,
      "winRate": 0,
      "netProfitPct": 0,
      "profitFactor": 0,
      "maxDrawdownPct": 0,
      "v10Trades": 2,
      "v10WinRate": 50,
      "v10PF": 1.8532506081443116,
      "v6PF": 0,
      "pfDelta10": -1.8532506081443116,
      "pfDelta6": 0
    },
    {
      "symbol": "SZSE:301033",
      "totalTrades": 1,
      "wins": 0,
      "losses": 1,
      "winRate": 0,
      "netProfitPct": -0.7171603820000004,
      "profitFactor": 0,
      "maxDrawdownPct": 0.7282569879999937,
      "v10Trades": 1,
      "v10WinRate": 0,
      "v10PF": 0,
      "v6PF": 0,
      "pfDelta10": 0,
      "pfDelta6": 0
    },
    {
      "symbol": "SSE:600885",
      "totalTrades": 13,
      "wins": 8,
      "losses": 5,
      "winRate": 61.53846153846154,
      "netProfitPct": 0.5160635099999991,
      "profitFactor": 1.211720880796492,
      "maxDrawdownPct": 2.544510396739681,
      "v10Trades": 25,
      "v10WinRate": 56.00000000000001,
      "v10PF": 1.470864964924832,
      "v6PF": 1.401,
      "pfDelta10": -0.2591440841283399,
      "pfDelta6": -0.18927911920350793
    },
    {
      "symbol": "SZSE:002850",
      "totalTrades": 2,
      "wins": 2,
      "losses": 0,
      "winRate": 100,
      "netProfitPct": 1.574008721,
      "profitFactor": 0,
      "maxDrawdownPct": 0.3769939860000013,
      "v10Trades": 3,
      "v10WinRate": 66.66666666666666,
      "v10PF": 3.2246693347837136,
      "v6PF": 0,
      "pfDelta10": -3.2246693347837136,
      "pfDelta6": 0
    },
    {
      "symbol": "SZSE:002353",
      "totalTrades": 10,
      "wins": 5,
      "losses": 5,
      "winRate": 50,
      "netProfitPct": -0.7180504000000005,
      "profitFactor": 0.701024030120339,
      "maxDrawdownPct": 2.111808851581715,
      "v10Trades": 12,
      "v10WinRate": 58.333333333333336,
      "v10PF": 1.3487939384239707,
      "v6PF": 1.522,
      "pfDelta10": -0.6477699083036317,
      "pfDelta6": -0.820975969879661
    },
    {
      "symbol": "SSE:600686",
      "totalTrades": 1,
      "wins": 0,
      "losses": 1,
      "winRate": 0,
      "netProfitPct": -0.48263190799999944,
      "profitFactor": 0,
      "maxDrawdownPct": 0.5008272999999899,
      "v10Trades": 6,
      "v10WinRate": 33.33333333333333,
      "v10PF": 0.6281854122792705,
      "v6PF": 1.02,
      "pfDelta10": -0.6281854122792705,
      "pfDelta6": -1.02
    },
    {
      "symbol": "SSE:603239",
      "totalTrades": 4,
      "wins": 2,
      "losses": 2,
      "winRate": 50,
      "netProfitPct": -1.0419858460000009,
      "profitFactor": 0.6158377897879526,
      "maxDrawdownPct": 2.726921046000003,
      "v10Trades": 6,
      "v10WinRate": 33.33333333333333,
      "v10PF": 0.8932792024961937,
      "v6PF": 0.823,
      "pfDelta10": -0.2774414127082412,
      "pfDelta6": -0.2071622102120474
    },
    {
      "symbol": "SSE:603199",
      "totalTrades": 2,
      "wins": 0,
      "losses": 2,
      "winRate": 0,
      "netProfitPct": -0.9934925500000015,
      "profitFactor": 0,
      "maxDrawdownPct": 0.9934925499999954,
      "v10Trades": 3,
      "v10WinRate": 0,
      "v10PF": 0,
      "v6PF": 0,
      "pfDelta10": 0,
      "pfDelta6": 0
    },
    {
      "symbol": "SZSE:300019",
      "totalTrades": 1,
      "wins": 0,
      "losses": 1,
      "winRate": 0,
      "netProfitPct": -0.3718161140000003,
      "profitFactor": 0,
      "maxDrawdownPct": 0.6064028970000073,
      "v10Trades": 3,
      "v10WinRate": 0,
      "v10PF": 0,
      "v6PF": 0,
      "pfDelta10": 0,
      "pfDelta6": 0
    },
    {
      "symbol": "SZSE:000957",
      "totalTrades": 6,
      "wins": 0,
      "losses": 6,
      "winRate": 0,
      "netProfitPct": -3.335581640000002,
      "profitFactor": 0,
      "maxDrawdownPct": 3.3355816400000036,
      "v10Trades": 9,
      "v10WinRate": 0,
      "v10PF": 0,
      "v6PF": 0,
      "pfDelta10": 0,
      "pfDelta6": 0
    },
    {
      "symbol": "SZSE:002468",
      "totalTrades": 3,
      "wins": 2,
      "losses": 1,
      "winRate": 66.66666666666666,
      "netProfitPct": 0.4998704539999994,
      "profitFactor": 1.871222178091321,
      "maxDrawdownPct": 0.5735165784087065,
      "v10Trades": 5,
      "v10WinRate": 40,
      "v10PF": 0.8434935901015174,
      "v6PF": 1.165,
      "pfDelta10": 1.0277285879898037,
      "pfDelta6": 0.7062221780913209
    },
    {
      "symbol": "SSE:600660",
      "totalTrades": 7,
      "wins": 6,
      "losses": 1,
      "winRate": 85.71428571428571,
      "netProfitPct": 3.0423133100000004,
      "profitFactor": 13.980567859620647,
      "maxDrawdownPct": 0.31299460834882026,
      "v10Trades": 10,
      "v10WinRate": 60,
      "v10PF": 3.5031357712306925,
      "v6PF": 4.145,
      "pfDelta10": 10.477432088389955,
      "pfDelta6": 9.835567859620648
    },
    {
      "symbol": "SSE:605599",
      "totalTrades": 3,
      "wins": 2,
      "losses": 1,
      "winRate": 66.66666666666666,
      "netProfitPct": 1.3522267859999983,
      "profitFactor": 5.133956876903102,
      "maxDrawdownPct": 0.6836776267862493,
      "v10Trades": 4,
      "v10WinRate": 75,
      "v10PF": 5.081793710358334,
      "v6PF": 3.89,
      "pfDelta10": 0.05216316654476749,
      "pfDelta6": 1.2439568769031015
    },
    {
      "symbol": "SSE:603706",
      "totalTrades": 4,
      "wins": 4,
      "losses": 0,
      "winRate": 100,
      "netProfitPct": 2.1167025320000015,
      "profitFactor": 0,
      "maxDrawdownPct": 0.3949743183423301,
      "v10Trades": 4,
      "v10WinRate": 75,
      "v10PF": 28.857800912319604,
      "v6PF": 0,
      "pfDelta10": -28.857800912319604,
      "pfDelta6": 0
    },
    {
      "symbol": "SZSE:300357",
      "totalTrades": 6,
      "wins": 4,
      "losses": 2,
      "winRate": 66.66666666666666,
      "netProfitPct": 1.3720747980000005,
      "profitFactor": 4.303827566939502,
      "maxDrawdownPct": 0.39252323586974325,
      "v10Trades": 8,
      "v10WinRate": 75,
      "v10PF": 7.673424716106807,
      "v6PF": 7.654,
      "pfDelta10": -3.369597149167306,
      "pfDelta6": -3.3501724330604983
    },
    {
      "symbol": "SSE:600160",
      "totalTrades": 3,
      "wins": 2,
      "losses": 1,
      "winRate": 66.66666666666666,
      "netProfitPct": 0.3348239199999998,
      "profitFactor": 1.8180792128603454,
      "maxDrawdownPct": 0.6180255630000029,
      "v10Trades": 4,
      "v10WinRate": 50,
      "v10PF": 0.7814345166988135,
      "v6PF": 0.691,
      "pfDelta10": 1.0366446961615319,
      "pfDelta6": 1.1270792128603455
    },
    {
      "symbol": "SZSE:300750",
      "totalTrades": 0,
      "wins": 0,
      "losses": 0,
      "winRate": 0,
      "netProfitPct": 0,
      "profitFactor": 0,
      "maxDrawdownPct": 0,
      "v10Trades": 2,
      "v10WinRate": 0,
      "v10PF": 0,
      "v6PF": 0,
      "pfDelta10": 0,
      "pfDelta6": 0
    },
    {
      "symbol": "SSE:600983",
      "totalTrades": 5,
      "wins": 2,
      "losses": 3,
      "winRate": 40,
      "netProfitPct": 1.1187976719999984,
      "profitFactor": 1.5610849791222956,
      "maxDrawdownPct": 2.607932925000001,
      "v10Trades": 10,
      "v10WinRate": 40,
      "v10PF": 1.050940712943705,
      "v6PF": 0.295,
      "pfDelta10": 0.5101442661785907,
      "pfDelta6": 1.2660849791222957
    },
    {
      "symbol": "SZSE:002469",
      "totalTrades": 3,
      "wins": 0,
      "losses": 3,
      "winRate": 0,
      "netProfitPct": -1.465677176000003,
      "profitFactor": 0,
      "maxDrawdownPct": 1.5092121999999943,
      "v10Trades": 4,
      "v10WinRate": 0,
      "v10PF": 0,
      "v6PF": 0,
      "pfDelta10": 0,
      "pfDelta6": 0
    },
    {
      "symbol": "SZSE:002901",
      "totalTrades": 2,
      "wins": 0,
      "losses": 2,
      "winRate": 0,
      "netProfitPct": -1.5630562590000001,
      "profitFactor": 0,
      "maxDrawdownPct": 1.6813943940000027,
      "v10Trades": 3,
      "v10WinRate": 0,
      "v10PF": 0,
      "v6PF": 0,
      "pfDelta10": 0,
      "pfDelta6": 0
    },
    {
      "symbol": "SZSE:301109",
      "totalTrades": 2,
      "wins": 2,
      "losses": 0,
      "winRate": 100,
      "netProfitPct": 1.7394490200000001,
      "profitFactor": 0,
      "maxDrawdownPct": 0.022112726000006657,
      "v10Trades": 4,
      "v10WinRate": 100,
      "v10PF": 0,
      "v6PF": 0,
      "pfDelta10": 0,
      "pfDelta6": 0
    },
    {
      "symbol": "SZSE:003006",
      "totalTrades": 0,
      "wins": 0,
      "losses": 0,
      "winRate": 0,
      "netProfitPct": 0,
      "profitFactor": 0,
      "maxDrawdownPct": 0,
      "v10Trades": 1,
      "v10WinRate": 0,
      "v10PF": 0,
      "v6PF": 0,
      "pfDelta10": 0,
      "pfDelta6": 0
    },
    {
      "symbol": "SSE:603508",
      "totalTrades": 2,
      "wins": 0,
      "losses": 2,
      "winRate": 0,
      "netProfitPct": -1.9996075890000014,
      "profitFactor": 0,
      "maxDrawdownPct": 2.126230839000011,
      "v10Trades": 6,
      "v10WinRate": 50,
      "v10PF": 1.4275342662694483,
      "v6PF": 0.056,
      "pfDelta10": -1.4275342662694483,
      "pfDelta6": -0.056
    },
    {
      "symbol": "SSE:603606",
      "totalTrades": 9,
      "wins": 6,
      "losses": 3,
      "winRate": 66.66666666666666,
      "netProfitPct": 1.4428545420000032,
      "profitFactor": 2.2496584437901617,
      "maxDrawdownPct": 0.9743377000000037,
      "v10Trades": 11,
      "v10WinRate": 45.45454545454545,
      "v10PF": 1.3146812485386496,
      "v6PF": 2.73,
      "pfDelta10": 0.934977195251512,
      "pfDelta6": -0.4803415562098383
    },
    {
      "symbol": "SZSE:300505",
      "totalTrades": 7,
      "wins": 6,
      "losses": 1,
      "winRate": 85.71428571428571,
      "netProfitPct": 1.8793656540000006,
      "profitFactor": 9.351419722195008,
      "maxDrawdownPct": 0.8372667260000016,
      "v10Trades": 8,
      "v10WinRate": 75,
      "v10PF": 7.442805865272128,
      "v6PF": 1.471,
      "pfDelta10": 1.90861385692288,
      "pfDelta6": 7.880419722195008
    },
    {
      "symbol": "SSE:601022",
      "totalTrades": 1,
      "wins": 0,
      "losses": 1,
      "winRate": 0,
      "netProfitPct": -0.37536459400000005,
      "profitFactor": 0,
      "maxDrawdownPct": 0.4718677700000117,
      "v10Trades": 1,
      "v10WinRate": 0,
      "v10PF": 0,
      "v6PF": 0,
      "pfDelta10": 0,
      "pfDelta6": 0
    },
    {
      "symbol": "SZSE:002245",
      "totalTrades": 4,
      "wins": 4,
      "losses": 0,
      "winRate": 100,
      "netProfitPct": 1.148126369000001,
      "profitFactor": 0,
      "maxDrawdownPct": 0.4983832819360138,
      "v10Trades": 7,
      "v10WinRate": 85.71428571428571,
      "v10PF": 5.747265380200569,
      "v6PF": 4.487,
      "pfDelta10": -5.747265380200569,
      "pfDelta6": -4.487
    },
    {
      "symbol": "SZSE:300703",
      "totalTrades": 2,
      "wins": 2,
      "losses": 0,
      "winRate": 100,
      "netProfitPct": 2.3193067819999995,
      "profitFactor": 0,
      "maxDrawdownPct": 0.07096736999999848,
      "v10Trades": 6,
      "v10WinRate": 33.33333333333333,
      "v10PF": 0.79746741744033,
      "v6PF": 1.364,
      "pfDelta10": -0.79746741744033,
      "pfDelta6": -1.364
    },
    {
      "symbol": "SZSE:002891",
      "totalTrades": 3,
      "wins": 0,
      "losses": 3,
      "winRate": 0,
      "netProfitPct": -2.8670723440000008,
      "profitFactor": 0,
      "maxDrawdownPct": 2.867072344,
      "v10Trades": 4,
      "v10WinRate": 0,
      "v10PF": 0,
      "v6PF": 0.026,
      "pfDelta10": 0,
      "pfDelta6": -0.026
    },
    {
      "symbol": "SZSE:300408",
      "totalTrades": 8,
      "wins": 4,
      "losses": 4,
      "winRate": 50,
      "netProfitPct": 1.0648133459999967,
      "profitFactor": 1.7347621211398776,
      "maxDrawdownPct": 1.2313128477390933,
      "v10Trades": 10,
      "v10WinRate": 40,
      "v10PF": 1.1274217340312582,
      "v6PF": 1.231,
      "pfDelta10": 0.6073403871086194,
      "pfDelta6": 0.5037621211398775
    },
    {
      "symbol": "SZSE:002284",
      "totalTrades": 1,
      "wins": 0,
      "losses": 1,
      "winRate": 0,
      "netProfitPct": -1.3367065800000004,
      "profitFactor": 0,
      "maxDrawdownPct": 1.3367065799999982,
      "v10Trades": 2,
      "v10WinRate": 0,
      "v10PF": 0,
      "v6PF": 0,
      "pfDelta10": 0,
      "pfDelta6": 0
    },
    {
      "symbol": "SZSE:300882",
      "totalTrades": 1,
      "wins": 0,
      "losses": 1,
      "winRate": 0,
      "netProfitPct": -0.35111189099999995,
      "profitFactor": 0,
      "maxDrawdownPct": 0.5882028080000018,
      "v10Trades": 1,
      "v10WinRate": 0,
      "v10PF": 0,
      "v6PF": 0,
      "pfDelta10": 0,
      "pfDelta6": 0
    },
    {
      "symbol": "SZSE:002489",
      "totalTrades": 2,
      "wins": 0,
      "losses": 2,
      "winRate": 0,
      "netProfitPct": -1.0480347790000002,
      "profitFactor": 0,
      "maxDrawdownPct": 1.3188042129999957,
      "v10Trades": 4,
      "v10WinRate": 0,
      "v10PF": 0,
      "v6PF": 0,
      "pfDelta10": 0,
      "pfDelta6": 0
    },
    {
      "symbol": "SSE:603103",
      "totalTrades": 3,
      "wins": 0,
      "losses": 3,
      "winRate": 0,
      "netProfitPct": -1.3273802370000003,
      "profitFactor": 0,
      "maxDrawdownPct": 1.7359802370000108,
      "v10Trades": 5,
      "v10WinRate": 60,
      "v10PF": 0.22005971680380512,
      "v6PF": 0.194,
      "pfDelta10": -0.22005971680380512,
      "pfDelta6": -0.194
    },
    {
      "symbol": "SSE:605319",
      "totalTrades": 2,
      "wins": 2,
      "losses": 0,
      "winRate": 100,
      "netProfitPct": 0.728816088,
      "profitFactor": 0,
      "maxDrawdownPct": 0.052241831999999704,
      "v10Trades": 2,
      "v10WinRate": 50,
      "v10PF": 2.0434820847478505,
      "v6PF": 0,
      "pfDelta10": -2.0434820847478505,
      "pfDelta6": 0
    },
    {
      "symbol": "SSE:603025",
      "totalTrades": 2,
      "wins": 2,
      "losses": 0,
      "winRate": 100,
      "netProfitPct": 1.1187486349999987,
      "profitFactor": 0,
      "maxDrawdownPct": 0.17635138500000175,
      "v10Trades": 3,
      "v10WinRate": 66.66666666666666,
      "v10PF": 3.1796746087170664,
      "v6PF": 36.505,
      "pfDelta10": -3.1796746087170664,
      "pfDelta6": -36.505
    },
    {
      "symbol": "SSE:603062",
      "totalTrades": 0,
      "wins": 0,
      "losses": 0,
      "winRate": 0,
      "netProfitPct": 0,
      "profitFactor": 0,
      "maxDrawdownPct": 0,
      "v10Trades": 3,
      "v10WinRate": 66.66666666666666,
      "v10PF": 5.7207337398965805,
      "v6PF": 9.916,
      "pfDelta10": -5.7207337398965805,
      "pfDelta6": -9.916
    },
    {
      "symbol": "SZSE:001328",
      "totalTrades": 1,
      "wins": 0,
      "losses": 1,
      "winRate": 0,
      "netProfitPct": -0.17540386400000052,
      "profitFactor": 0,
      "maxDrawdownPct": 0.2605974229999993,
      "v10Trades": 1,
      "v10WinRate": 0,
      "v10PF": 0,
      "v6PF": 0,
      "pfDelta10": 0,
      "pfDelta6": 0
    },
    {
      "symbol": "SZSE:301138",
      "totalTrades": 3,
      "wins": 2,
      "losses": 1,
      "winRate": 66.66666666666666,
      "netProfitPct": -0.09814214400000071,
      "profitFactor": 0.8845735047714527,
      "maxDrawdownPct": 1.0688054879999982,
      "v10Trades": 3,
      "v10WinRate": 66.66666666666666,
      "v10PF": 1.8722141305476887,
      "v6PF": 0,
      "pfDelta10": -0.987640625776236,
      "pfDelta6": 0.8845735047714527
    },
    {
      "symbol": "SZSE:001319",
      "totalTrades": 0,
      "wins": 0,
      "losses": 0,
      "winRate": 0,
      "netProfitPct": 0,
      "profitFactor": 0,
      "maxDrawdownPct": 0,
      "v10Trades": 1,
      "v10WinRate": 0,
      "v10PF": 0,
      "v6PF": 0,
      "pfDelta10": 0,
      "pfDelta6": 0
    },
    {
      "symbol": "SZSE:300577",
      "totalTrades": 2,
      "wins": 0,
      "losses": 2,
      "winRate": 0,
      "netProfitPct": -1.7698792250000004,
      "profitFactor": 0,
      "maxDrawdownPct": 1.769879224999997,
      "v10Trades": 6,
      "v10WinRate": 33.33333333333333,
      "v10PF": 0.6811848527178818,
      "v6PF": 0.619,
      "pfDelta10": -0.6811848527178818,
      "pfDelta6": -0.619
    },
    {
      "symbol": "SZSE:000657",
      "totalTrades": 1,
      "wins": 0,
      "losses": 1,
      "winRate": 0,
      "netProfitPct": -0.58580361,
      "profitFactor": 0,
      "maxDrawdownPct": 0.5858036100000027,
      "v10Trades": 2,
      "v10WinRate": 0,
      "v10PF": 0,
      "v6PF": 0,
      "pfDelta10": 0,
      "pfDelta6": 0
    },
    {
      "symbol": "SSE:600176",
      "totalTrades": 6,
      "wins": 2,
      "losses": 4,
      "winRate": 33.33333333333333,
      "netProfitPct": -1.0068414640000012,
      "profitFactor": 0.5001986278671323,
      "maxDrawdownPct": 2.1191737490000087,
      "v10Trades": 8,
      "v10WinRate": 0,
      "v10PF": 0,
      "v6PF": 0,
      "pfDelta10": 0.5001986278671323,
      "pfDelta6": 0.5001986278671323
    },
    {
      "symbol": "SZSE:300743",
      "totalTrades": 1,
      "wins": 0,
      "losses": 1,
      "winRate": 0,
      "netProfitPct": -0.7719539889999993,
      "profitFactor": 0,
      "maxDrawdownPct": 1.0393967459999984,
      "v10Trades": 3,
      "v10WinRate": 66.66666666666666,
      "v10PF": 0.65446469634086,
      "v6PF": 1.114,
      "pfDelta10": -0.65446469634086,
      "pfDelta6": -1.114
    },
    {
      "symbol": "SZSE:002056",
      "totalTrades": 9,
      "wins": 4,
      "losses": 5,
      "winRate": 44.44444444444444,
      "netProfitPct": -0.9306832210000004,
      "profitFactor": 0.6736946293278201,
      "maxDrawdownPct": 2.731681030409336,
      "v10Trades": 14,
      "v10WinRate": 35.714285714285715,
      "v10PF": 0.5729519887152247,
      "v6PF": 0.668,
      "pfDelta10": 0.10074264061259541,
      "pfDelta6": 0.0056946293278200555
    },
    {
      "symbol": "SSE:605198",
      "totalTrades": 2,
      "wins": 2,
      "losses": 0,
      "winRate": 100,
      "netProfitPct": 1.5384064960000001,
      "profitFactor": 0,
      "maxDrawdownPct": 0.1580849600000074,
      "v10Trades": 4,
      "v10WinRate": 100,
      "v10PF": 0,
      "v6PF": 37.78,
      "pfDelta10": 0,
      "pfDelta6": -37.78
    },
    {
      "symbol": "SZSE:002803",
      "totalTrades": 3,
      "wins": 2,
      "losses": 1,
      "winRate": 66.66666666666666,
      "netProfitPct": 0.7335320020000006,
      "profitFactor": 2.0372612999633053,
      "maxDrawdownPct": 0.7532833530246568,
      "v10Trades": 4,
      "v10WinRate": 50,
      "v10PF": 1.1723853452897492,
      "v6PF": 1.158,
      "pfDelta10": 0.864875954673556,
      "pfDelta6": 0.8792612999633054
    },
    {
      "symbol": "SZSE:301303",
      "totalTrades": 1,
      "wins": 0,
      "losses": 1,
      "winRate": 0,
      "netProfitPct": -0.18681822199999998,
      "profitFactor": 0,
      "maxDrawdownPct": 0.19090618600000742,
      "v10Trades": 1,
      "v10WinRate": 0,
      "v10PF": 0,
      "v6PF": 0,
      "pfDelta10": 0,
      "pfDelta6": 0
    },
    {
      "symbol": "SSE:600406",
      "totalTrades": 3,
      "wins": 0,
      "losses": 3,
      "winRate": 0,
      "netProfitPct": -2.031541333,
      "profitFactor": 0,
      "maxDrawdownPct": 2.2370049880000007,
      "v10Trades": 9,
      "v10WinRate": 33.33333333333333,
      "v10PF": 0.5656971454411199,
      "v6PF": 0.571,
      "pfDelta10": -0.5656971454411199,
      "pfDelta6": -0.571
    },
    {
      "symbol": "SZSE:002096",
      "totalTrades": 8,
      "wins": 4,
      "losses": 4,
      "winRate": 50,
      "netProfitPct": -0.08087898200000086,
      "profitFactor": 0.9520795397318365,
      "maxDrawdownPct": 1.2880354020000087,
      "v10Trades": 12,
      "v10WinRate": 41.66666666666667,
      "v10PF": 0.8299378466146353,
      "v6PF": 0.787,
      "pfDelta10": 0.12214169311720113,
      "pfDelta6": 0.16507953973183642
    },
    {
      "symbol": "SSE:603659",
      "totalTrades": 4,
      "wins": 2,
      "losses": 2,
      "winRate": 50,
      "netProfitPct": -0.027877036999999064,
      "profitFactor": 0.9580587198927484,
      "maxDrawdownPct": 0.959878773999997,
      "v10Trades": 4,
      "v10WinRate": 25,
      "v10PF": 0.6205900910197791,
      "v6PF": 1.683,
      "pfDelta10": 0.33746862887296925,
      "pfDelta6": -0.7249412801072517
    }
  ]
}