{
  "generated_at": "2026-07-03T06:42:40.464Z",
  "market": "cn",
  "source": "./watchlist/cn_selected.txt",
  "total": 30,
  "success": 30,
  "failed": [],
  "results": [
    {
      "symbol": "SZSE:002875",
      "name": "安奈儿",
      "ok": true,
      "price": 14.86,
      "open": 14.85,
      "high": 15.07,
      "low": 14.58,
      "gap_pct": 0.000673,
      "close_vs_low": 1.019204,
      "atr_pct": 1.4
    },
    {
      "symbol": "SSE:603259",
      "name": "药明康德",
      "ok": true,
      "price": 124.02,
      "open": 123.6,
      "high": 125.06,
      "low": 119.52,
      "gap_pct": 0.003398,
      "close_vs_low": 1.037651,
      "atr_pct": 1.9
    },
    {
      "symbol": "SSE:600688",
      "name": "上海石化",
      "ok": true,
      "price": 2.93,
      "open": 2.94,
      "high": 2.99,
      "low": 2.91,
      "gap_pct": 0.003401,
      "close_vs_low": 1.006873,
      "atr_pct": 5.2
    },
    {
      "symbol": "SSE:600522",
      "name": "中天科技",
      "ok": true,
      "price": 50.63,
      "open": 50.82,
      "high": 52.5,
      "low": 50.25,
      "gap_pct": 0.003739,
      "close_vs_low": 1.007562,
      "atr_pct": 7.9
    },
    {
      "symbol": "SZSE:000776",
      "name": "广发证券",
      "ok": true,
      "price": 23.76,
      "open": 23.92,
      "high": 24.16,
      "low": 23.3,
      "gap_pct": 0.006689,
      "close_vs_low": 1.019742,
      "atr_pct": 3.3
    },
    {
      "symbol": "SZSE:001223",
      "name": "欧克科技",
      "ok": true,
      "price": 42.84,
      "open": 42.5,
      "high": 44.08,
      "low": 41.15,
      "gap_pct": 0.008,
      "close_vs_low": 1.041069,
      "atr_pct": 6.6
    },
    {
      "symbol": "SZSE:300037",
      "name": "300037",
      "ok": true,
      "price": 89.42,
      "open": 88.37,
      "high": 93.88,
      "low": 87.2,
      "gap_pct": 0.011882,
      "close_vs_low": 1.025459,
      "atr_pct": 2.6
    },
    {
      "symbol": "SZSE:002452",
      "name": "长高电气",
      "ok": true,
      "price": 12.94,
      "open": 12.7,
      "high": 13.25,
      "low": 12.58,
      "gap_pct": 0.018898,
      "close_vs_low": 1.028617,
      "atr_pct": 2.9
    },
    {
      "symbol": "SZSE:159389",
      "name": "数字经济ETF嘉实",
      "ok": true,
      "price": 2.109,
      "open": 2.066,
      "high": 2.166,
      "low": 2.057,
      "gap_pct": 0.020813,
      "close_vs_low": 1.02528,
      "atr_pct": 2.5
    },
    {
      "symbol": "SSE:605162",
      "name": "新中港",
      "ok": true,
      "price": 8.01,
      "open": 7.83,
      "high": 8.09,
      "low": 7.66,
      "gap_pct": 0.022989,
      "close_vs_low": 1.045692,
      "atr_pct": 2
    },
    {
      "symbol": "SSE:601798",
      "name": "601798",
      "ok": true,
      "price": 7.41,
      "open": 7.24,
      "high": 7.52,
      "low": 7.24,
      "gap_pct": 0.023481,
      "close_vs_low": 1.023481,
      "atr_pct": 3
    },
    {
      "symbol": "SZSE:159819",
      "name": "人工智能ETF易方达",
      "ok": true,
      "price": 2.048,
      "open": 2.001,
      "high": 2.098,
      "low": 2,
      "gap_pct": 0.023488,
      "close_vs_low": 1.024,
      "atr_pct": 2.5
    },
    {
      "symbol": "SSE:600198",
      "name": "600198",
      "ok": true,
      "price": 9.12,
      "open": 9.35,
      "high": 9.66,
      "low": 9.07,
      "gap_pct": 0.024599,
      "close_vs_low": 1.005513,
      "atr_pct": 6.6
    },
    {
      "symbol": "SZSE:002600",
      "name": "领益智造",
      "ok": true,
      "price": 18.03,
      "open": 17.54,
      "high": 18.46,
      "low": 17.12,
      "gap_pct": 0.027936,
      "close_vs_low": 1.053154,
      "atr_pct": 2.3
    },
    {
      "symbol": "SSE:600186",
      "name": "莲花控股",
      "ok": true,
      "price": 11.89,
      "open": 12.25,
      "high": 12.38,
      "low": 11.86,
      "gap_pct": 0.029388,
      "close_vs_low": 1.00253,
      "atr_pct": 2.3
    },
    {
      "symbol": "SZSE:300857",
      "name": "协创数据",
      "ok": true,
      "price": 302.26,
      "open": 293.59,
      "high": 309.8,
      "low": 289.23,
      "gap_pct": 0.029531,
      "close_vs_low": 1.045051,
      "atr_pct": 7.4
    },
    {
      "symbol": "SZSE:300054",
      "name": "鼎龙股份",
      "ok": true,
      "price": 90.19,
      "open": 92.99,
      "high": 93.71,
      "low": 88.21,
      "gap_pct": 0.030111,
      "close_vs_low": 1.022446,
      "atr_pct": 2.9
    },
    {
      "symbol": "SZSE:002965",
      "name": "祥鑫科技",
      "ok": true,
      "price": 52.7,
      "open": 50.77,
      "high": 53.5,
      "low": 49.13,
      "gap_pct": 0.038015,
      "close_vs_low": 1.072664,
      "atr_pct": 2
    },
    {
      "symbol": "SSE:600176",
      "name": "中国巨石",
      "ok": true,
      "price": 70.98,
      "open": 68.18,
      "high": 74.6,
      "low": 65.51,
      "gap_pct": 0.041068,
      "close_vs_low": 1.083499,
      "atr_pct": 2.2
    },
    {
      "symbol": "SSE:600172",
      "name": "黄河旋风",
      "ok": true,
      "price": 16.93,
      "open": 17.66,
      "high": 17.76,
      "low": 16.24,
      "gap_pct": 0.041336,
      "close_vs_low": 1.042488,
      "atr_pct": 6.1
    },
    {
      "symbol": "SZSE:000725",
      "name": "京东方Ａ",
      "ok": true,
      "price": 8.46,
      "open": 8.86,
      "high": 9.09,
      "low": 8.31,
      "gap_pct": 0.045147,
      "close_vs_low": 1.018051,
      "atr_pct": 8
    },
    {
      "symbol": "SSE:603120",
      "name": "603120",
      "ok": true,
      "price": 57.25,
      "open": 60.13,
      "high": 61.72,
      "low": 56.78,
      "gap_pct": 0.047896,
      "close_vs_low": 1.008278,
      "atr_pct": 2.8
    },
    {
      "symbol": "SSE:603203",
      "name": "快克智能",
      "ok": true,
      "price": 59.18,
      "open": 62.2,
      "high": 62.88,
      "low": 58.31,
      "gap_pct": 0.048553,
      "close_vs_low": 1.01492,
      "atr_pct": 1.9
    },
    {
      "symbol": "SZSE:300990",
      "name": "同飞股份",
      "ok": true,
      "price": 100.39,
      "open": 95.43,
      "high": 103.12,
      "low": 95.4,
      "gap_pct": 0.051975,
      "close_vs_low": 1.052306,
      "atr_pct": 2.4
    },
    {
      "symbol": "SZSE:301308",
      "name": "江波龙",
      "ok": true,
      "price": 619.71,
      "open": 589,
      "high": 646.85,
      "low": 574.1,
      "gap_pct": 0.052139,
      "close_vs_low": 1.079446,
      "atr_pct": 3.7
    },
    {
      "symbol": "SZSE:002056",
      "name": "横店东磁",
      "ok": true,
      "price": 33.17,
      "open": 31.11,
      "high": 33.73,
      "low": 29.11,
      "gap_pct": 0.066217,
      "close_vs_low": 1.139471,
      "atr_pct": 8
    },
    {
      "symbol": "SZSE:002916",
      "name": "深南电路",
      "ok": true,
      "price": 454.94,
      "open": 426.28,
      "high": 465.41,
      "low": 415,
      "gap_pct": 0.067233,
      "close_vs_low": 1.096241,
      "atr_pct": 3
    },
    {
      "symbol": "SSE:600549",
      "name": "厦门钨业",
      "ok": true,
      "price": 75.36,
      "open": 81.2,
      "high": 81.9,
      "low": 74.88,
      "gap_pct": 0.071921,
      "close_vs_low": 1.00641,
      "atr_pct": 6.4
    },
    {
      "symbol": "SSE:600160",
      "name": "600160",
      "ok": true,
      "price": 49.35,
      "open": 53.51,
      "high": 54.68,
      "low": 49.35,
      "gap_pct": 0.077742,
      "close_vs_low": 1,
      "atr_pct": 2.6
    },
    {
      "symbol": "SZSE:001309",
      "name": "德明利",
      "ok": true,
      "price": 879.1,
      "open": 804.75,
      "high": 892.1,
      "low": 795,
      "gap_pct": 0.092389,
      "close_vs_low": 1.105786,
      "atr_pct": 3.7
    }
  ]
}